MEDS_tabular_automl/__init__.py
MEDS_tabular_automl/base_model.py
MEDS_tabular_automl/describe_codes.py
MEDS_tabular_automl/evaluation_callback.py
MEDS_tabular_automl/file_name.py
MEDS_tabular_automl/generate_static_features.py
MEDS_tabular_automl/generate_summarized_reps.py
MEDS_tabular_automl/generate_ts_features.py
MEDS_tabular_automl/mapper.py
MEDS_tabular_automl/sklearn_model.py
MEDS_tabular_automl/tabular_dataset.py
MEDS_tabular_automl/utils.py
MEDS_tabular_automl/xgboost_model.py
MEDS_tabular_automl/configs/__init__.py
MEDS_tabular_automl/configs/default.yaml
MEDS_tabular_automl/configs/describe_codes.yaml
MEDS_tabular_automl/configs/launch_model.yaml
MEDS_tabular_automl/configs/tabularization.yaml
MEDS_tabular_automl/configs/task_specific_caching.yaml
MEDS_tabular_automl/configs/hydra/callbacks/evaluation_callback.yaml
MEDS_tabular_automl/configs/model_launcher/__init__.py
MEDS_tabular_automl/configs/model_launcher/autogluon.yaml
MEDS_tabular_automl/configs/model_launcher/default.yaml
MEDS_tabular_automl/configs/model_launcher/knn_classifier.yaml
MEDS_tabular_automl/configs/model_launcher/logistic_regression.yaml
MEDS_tabular_automl/configs/model_launcher/random_forest_classifier.yaml
MEDS_tabular_automl/configs/model_launcher/sgd_classifier.yaml
MEDS_tabular_automl/configs/model_launcher/xgboost.yaml
MEDS_tabular_automl/configs/model_launcher/data_loading_params/__init__.py
MEDS_tabular_automl/configs/model_launcher/data_loading_params/default.yaml
MEDS_tabular_automl/configs/model_launcher/data_processing_params/__init__.py
MEDS_tabular_automl/configs/model_launcher/data_processing_params/default.yaml
MEDS_tabular_automl/configs/model_launcher/data_processing_params/imputer/__init__.py
MEDS_tabular_automl/configs/model_launcher/data_processing_params/imputer/default.yaml
MEDS_tabular_automl/configs/model_launcher/data_processing_params/imputer/mean_imputer.yaml
MEDS_tabular_automl/configs/model_launcher/data_processing_params/imputer/median_imputer.yaml
meds_tab-0.0.10.dist-info/LICENSE
meds_tab-0.0.10.dist-info/METADATA
meds_tab-0.0.10.dist-info/WHEEL
meds_tab-0.0.10.dist-info/entry_points.txt
meds_tab-0.0.10.dist-info/top_level.txt
meds_tab-0.0.10.dist-info/RECORD
