Metadata-Version: 2.2
Name: meds-tab
Version: 0.0.10
Summary: Scalable Tabularization of MEDS format Time-Series data
Author-email: Matthew McDermott <mattmcdermott8@gmail.com>, Nassim Oufattole <noufattole@gmail.com>, Teya Bergamaschi <teyabergamaschi@gmail.com>
Project-URL: Homepage, https://github.com/mmcdermott/MEDS_Tabular_AutoML
Project-URL: Issues, https://github.com/mmcdermott/MEDS_Tabular_AutoML/issues
Classifier: Programming Language :: Python :: 3
Classifier: License :: OSI Approved :: MIT License
Classifier: Operating System :: OS Independent
Requires-Python: >=3.11
License-File: LICENSE
Requires-Dist: polars<=1.17.1,>=1.6.0
Requires-Dist: pyarrow
Requires-Dist: loguru
Requires-Dist: hydra-core==1.3.2
Requires-Dist: numpy
Requires-Dist: scipy<1.14.0
Requires-Dist: pandas
Requires-Dist: tqdm
Requires-Dist: xgboost
Requires-Dist: scikit-learn
Requires-Dist: hydra-optuna-sweeper
Requires-Dist: hydra-joblib-launcher
Requires-Dist: ml-mixins
Requires-Dist: meds>=0.3.3
Requires-Dist: meds-transforms>=0.0.7
Requires-Dist: meds-evaluation
Provides-Extra: dev
Requires-Dist: pre-commit<4; extra == "dev"
Provides-Extra: tests
Requires-Dist: pytest; extra == "tests"
Requires-Dist: pytest-cov[toml]; extra == "tests"
Requires-Dist: rootutils; extra == "tests"
Provides-Extra: profiling
Requires-Dist: mprofile; extra == "profiling"
Requires-Dist: matplotlib; extra == "profiling"
Provides-Extra: autogluon
Requires-Dist: autogluon; python_version == "3.11.*" and extra == "autogluon"
Provides-Extra: docs
Requires-Dist: mkdocs==1.6.0; extra == "docs"
Requires-Dist: mkdocs-gen-files==0.5.0; extra == "docs"
Requires-Dist: mkdocs-get-deps==0.2.0; extra == "docs"
Requires-Dist: mkdocs-git-authors-plugin==0.9.0; extra == "docs"
Requires-Dist: mkdocs-git-revision-date-localized-plugin==1.2.7; extra == "docs"
Requires-Dist: mkdocs-literate-nav==0.6.1; extra == "docs"
Requires-Dist: mkdocs-material==9.5.33; extra == "docs"
Requires-Dist: mkdocs-material-extensions==1.3.1; extra == "docs"
Requires-Dist: mkdocs-section-index==0.3.9; extra == "docs"
Requires-Dist: mkdocs-snippets==1.3.0; extra == "docs"
Requires-Dist: mkdocstrings==0.25.2; extra == "docs"
Requires-Dist: mkdocstrings-python==1.10.8; extra == "docs"
